codelab_adapter_mqtt_client/__init__.py
codelab_adapter_mqtt_client/codelab_adapter_mqtt_client.py
codelab_adapter_mqtt_client/topic.py
codelab_adapter_mqtt_client/utils.py
codelab_adapter_mqtt_client/tools/monitor.py
codelab_adapter_mqtt_client/tools/trigger.py
codelab_adapter_mqtt_client-0.2.0.dist-info/AUTHORS.rst
codelab_adapter_mqtt_client-0.2.0.dist-info/LICENSE
codelab_adapter_mqtt_client-0.2.0.dist-info/METADATA
codelab_adapter_mqtt_client-0.2.0.dist-info/WHEEL
codelab_adapter_mqtt_client-0.2.0.dist-info/entry_points.txt
codelab_adapter_mqtt_client-0.2.0.dist-info/top_level.txt
codelab_adapter_mqtt_client-0.2.0.dist-info/RECORD
