Metadata-Version: 2.1
Name: codelab-adapter-mqtt-client
Version: 0.2.0
Summary: mqtt client for codelab_adapter
Home-page: https://github.com/wwj718/codelab_adapter_mqtt_client
Author: wenjie wu
Author-email: wuwenjie718@gmail.com
License: GNU General Public License v3
Keywords: codelab_adapter_mqtt_client
Platform: UNKNOWN
Classifier: Development Status :: 2 - Pre-Alpha
Classifier: Intended Audience :: Developers
Classifier: License :: OSI Approved :: GNU General Public License v3 (GPLv3)
Classifier: Natural Language :: English
Classifier: Programming Language :: Python :: 2
Classifier: Programming Language :: Python :: 2.7
Classifier: Programming Language :: Python :: 3
Classifier: Programming Language :: Python :: 3.4
Classifier: Programming Language :: Python :: 3.5
Classifier: Programming Language :: Python :: 3.6
Classifier: Programming Language :: Python :: 3.7
Requires-Dist: paho-mqtt
Requires-Dist: loguru (==0.3.2)
